[
	{
		"id": 1,
		"name": "Yannis Yang",
		"salary": 150000,
		"title": "Lawyer",
		"age": 51
	},
	{
		"id": 2,
		"name": "Yannis Schaefer",
		"salary": 75000,
		"title": "Engineer",
		"age": 31
	},
	{
		"id": 3,
		"name": "Marlon Thomson",
		"salary": 50000,
		"title": "HR",
		"age": 23
	},
	{
		"id": 4,
		"name": "Rhiann Fuller",
		"salary": 80000,
		"title": "Sales",
		"age": 18
	},
	{
		"id": 5,
		"name": "Gavin Garner",
		"salary": 60000,
		"title": "Janitor",
		"age": 43
	},
	{
		"id": 6,
		"name": "Nevaeh Harvey",
		"salary": 87000,
		"title": "Data Analyst",
		"age": 80
	},
	{
		"id": 7,
		"name": "Muhamed Ahmed",
		"salary": 95000,
		"title": "Developer",
		"age": 21
	}
]
